{
    "description": "Ippolito Cafici: un Nestore siciliano. Documenti inediti sulla vita e sull'opera Lorenzo Di Giovanni Osservazioni linguistiche sulla narrativa di Antonio Tabucchi. Piani del racconto, testualit\u00e0, sintassi", 
    "domain": "www.ledonline.it", 
    "identifiers": {}, 
    "is_part_of": {
        "title": "ACME", 
        "url": "http://www.ledonline.it/acme/index.html"
    }, 
    "keywords": [], 
    "language": [
        "it", 
        1.0
    ], 
    "provenance": [], 
    "related_resources": [], 
    "subordinate_resources": [], 
    "title": "Ippolito Cafici: un Nestore siciliano. Documenti inediti sulla vita e sull'opera", 
    "url": "http://www.ledonline.it/acme/allegati/Acme-11-II_12_Pace.pdf", 
    "volume": null, 
    "year": null, 
    "zotero_id": null
}