{
    "description": "Transoxiana 2, Julio 2001.", 
    "domain": "www.transoxiana.org", 
    "identifiers": {}, 
    "is_part_of": {
        "issn": "1666-7050", 
        "title": "Transoxiana: Journal Libre de Estudios Orientales", 
        "url": "http://www.transoxiana.org/"
    }, 
    "keywords": [], 
    "language": null, 
    "provenance": [
        {
            "fields": [
                "description", 
                "domain", 
                "identifiers", 
                "is_part_of", 
                "keywords", 
                "language", 
                "provenance", 
                "related_resources", 
                "subordinate_resources", 
                "title", 
                "url", 
                "volume", 
                "year", 
                "zotero_id"
            ], 
            "resource": "tag:blogger.com,1999:blog-116259103207720939.post-86106668535869170", 
            "resource_date": "2013-07-18T09:17:24.119-04:00", 
            "term": "http://purl.org/spar/cito/citesAsDataSource", 
            "when": "2015-06-13T16:15:24.621790"
        }, 
        {
            "resource": "http://ancientworldonline.blogspot.com/2009/09/open-access-journals-transoxiana.html", 
            "resource_date": "2013-07-18T09:17:24.119-04:00", 
            "term": "http://purl.org/spar/cito/citesAsMetadataDocument", 
            "when": "2015-06-13T16:15:24.621803"
        }
    ], 
    "related_resources": [], 
    "subordinate_resources": [], 
    "title": "Transoxiana 2, Julio 2001", 
    "url": "http://www.transoxiana.org/archivo.html#2", 
    "volume": null, 
    "year": null, 
    "zotero_id": null
}