{
    "authors": [], 
    "contributors": [], 
    "description": "Florin Gog\u00e2ltan, Victor Sava.", 
    "domain": "www.z-studarch.ro", 
    "editors": [], 
    "end_date": null, 
    "extent": null, 
    "form": null, 
    "frequency": null, 
    "identifiers": {}, 
    "is_part_of": {
        "title_full": "Ziridava Studia Archaeologica", 
        "url": "http://www.z-studarch.ro/index_e.html"
    }, 
    "issuance": null, 
    "issue": null, 
    "issued_dates": null, 
    "keywords": [], 
    "languages": [
        "en"
    ], 
    "places": [], 
    "provenance": [
        {
            "fields": [
                "authors", 
                "contributors", 
                "description", 
                "domain", 
                "editors", 
                "end_date", 
                "extent", 
                "form", 
                "frequency", 
                "identifiers", 
                "is_part_of", 
                "issuance", 
                "issue", 
                "issued_dates", 
                "keywords", 
                "languages", 
                "places", 
                "provenance", 
                "publishers", 
                "related_resources", 
                "responsibility", 
                "start_date", 
                "subordinate_resources", 
                "title", 
                "title_alternates", 
                "title_extended", 
                "type", 
                "url", 
                "url_alternates", 
                "volume", 
                "year", 
                "zenon_id", 
                "zotero_id"
            ], 
            "resource": "tag:blogger.com,1999:blog-116259103207720939.post-4976504329535684075", 
            "resource_date": "2015-06-01T13:23:54.170-04:00", 
            "term": "http://purl.org/spar/cito/citesAsDataSource", 
            "when": "2015-07-11T20:11:36.635129"
        }, 
        {
            "resource": "http://ancientworldonline.blogspot.com/2015/06/open-access-journal-ziridava-studia.html", 
            "resource_date": "2015-06-01T13:23:54.170-04:00", 
            "term": "http://purl.org/spar/cito/citesAsMetadataDocument", 
            "when": "2015-07-11T20:11:36.635146"
        }
    ], 
    "publishers": [], 
    "related_resources": [], 
    "resource_key": "0c669f52e45924015648d1d3f0f7c1648b885ee7", 
    "responsibility": [], 
    "start_date": null, 
    "subordinate_resources": [], 
    "title": "Environmental Changes in the Upperand Middle Tisza/Tisa Lowland during the Holocene", 
    "title_alternates": [], 
    "title_extended": null, 
    "type": null, 
    "url": "http://www.z-studarch.ro/2012_26/2%20daroczi.pdf", 
    "url_alternates": [], 
    "volume": null, 
    "year": null, 
    "zenon_id": null, 
    "zotero_id": null
}