{
    "description": "Verdolay 2005, n\u00ba 10, Revista del Museo Arqueol\u00f3gico, Segunda \u00e9poca 2007 Verdolay 2005, n\u00ba 9(Segunda \u00e9poca) 2005 Verdolay, n\u00ba8 1996 Verdolay, n\u00ba7 1995", 
    "domain": "www.museosdemurcia.com", 
    "identifiers": {}, 
    "is_part_of": {
        "issn": "1130-9776", 
        "title": "Verdolay", 
        "url": "http://www.museosdemurcia.com/arqueologicodemurcia/publicaciones/publicaciones_verdolay.php"
    }, 
    "keywords": [
        "museums", 
        "journal"
    ], 
    "language": [
        "es", 
        0.9999979031288544
    ], 
    "provenance": [
        {
            "fields": [
                "description", 
                "domain", 
                "identifiers", 
                "is_part_of", 
                "keywords", 
                "language", 
                "provenance", 
                "related_resources", 
                "subordinate_resources", 
                "title", 
                "url", 
                "volume", 
                "year", 
                "zotero_id"
            ], 
            "resource": "tag:blogger.com,1999:blog-116259103207720939.post-7825605953703750778", 
            "resource_date": "2012-04-12T07:26:30.845-04:00", 
            "term": "http://purl.org/spar/cito/citesAsDataSource", 
            "when": "2015-06-11T20:14:13.404380"
        }, 
        {
            "resource": "http://ancientworldonline.blogspot.com/2012/04/open-access-journal-verdolay.html", 
            "resource_date": "2012-04-12T07:26:30.845-04:00", 
            "term": "http://purl.org/spar/cito/citesAsMetadataDocument", 
            "when": "2015-06-11T20:14:13.404396"
        }
    ], 
    "related_resources": [], 
    "subordinate_resources": [], 
    "title": "Verdolay 2005, n\u00ba 10, Revista del Museo Arqueol\u00f3gico, Segunda \u00e9poca", 
    "url": "http://www.museosdemurcia.com/arqueologicodemurcia/publicaciones/verdolay10.pdf", 
    "volume": null, 
    "year": null, 
    "zotero_id": null
}