{
    "authors": [], 
    "contributors": [], 
    "description": "is the place for short pieces, quick reviews and informal articles on a vast variety of topics. There are also a frequently changing photo album contributed by readers, events and courses listings and our Discussion forum for asking questions, making suggestions and putting forward ideas. This section will be updated on an ad hoc basis. Expect to find a real mix of content here!.", 
    "domain": "www.egyptological.com", 
    "editors": [], 
    "end_date": null, 
    "extent": null, 
    "form": null, 
    "frequency": null, 
    "identifiers": {}, 
    "is_part_of": {
        "title_full": "Egyptological", 
        "url": "http://www.egyptological.com/"
    }, 
    "issuance": null, 
    "issue": null, 
    "issued_dates": null, 
    "keywords": [], 
    "languages": [
        "en"
    ], 
    "places": [], 
    "provenance": [
        {
            "fields": [
                "authors", 
                "contributors", 
                "description", 
                "domain", 
                "editors", 
                "end_date", 
                "extent", 
                "form", 
                "frequency", 
                "identifiers", 
                "is_part_of", 
                "issuance", 
                "issue", 
                "issued_dates", 
                "keywords", 
                "languages", 
                "places", 
                "provenance", 
                "publishers", 
                "related_resources", 
                "responsibility", 
                "start_date", 
                "subordinate_resources", 
                "title", 
                "title_alternates", 
                "title_extended", 
                "type", 
                "url", 
                "url_alternates", 
                "volume", 
                "year", 
                "zenon_id", 
                "zotero_id"
            ], 
            "resource": "tag:blogger.com,1999:blog-116259103207720939.post-2991059502125210979", 
            "resource_date": "2011-06-27T10:25:51.772-04:00", 
            "term": "http://purl.org/spar/cito/citesAsDataSource", 
            "when": "2015-07-11T20:07:58.900130"
        }, 
        {
            "resource": "http://ancientworldonline.blogspot.com/2011/04/new-open-access-journal-egyptological.html", 
            "resource_date": "2011-06-27T10:25:51.772-04:00", 
            "term": "http://purl.org/spar/cito/citesAsMetadataDocument", 
            "when": "2015-07-11T20:07:58.900142"
        }
    ], 
    "publishers": [], 
    "related_resources": [], 
    "resource_key": "colloquy", 
    "responsibility": [], 
    "start_date": null, 
    "subordinate_resources": [], 
    "title": "Colloquy", 
    "title_alternates": [], 
    "title_extended": null, 
    "type": null, 
    "url": "http://www.egyptological.com/colloquy", 
    "url_alternates": [], 
    "volume": null, 
    "year": null, 
    "zenon_id": null, 
    "zotero_id": null
}