{
    "description": "Cumulative Index forCounterfeit Coin Newsletter See the full List of Open Access Journals in Ancient Studies", 
    "domain": "www.coinauthentication.co.uk", 
    "identifiers": {}, 
    "is_part_of": {
        "title": "Counterfeit Coin Newsletter", 
        "url": "http://www.coinauthentication.co.uk/coininfo.html"
    }, 
    "keywords": [
        "journal", 
        "newsletter", 
        "open access", 
        "antiquity"
    ], 
    "language": [
        "en", 
        0.9999999999998803
    ], 
    "provenance": [], 
    "related_resources": [], 
    "subordinate_resources": [], 
    "title": "Cumulative Index forCounterfeit Coin Newsletter", 
    "url": "http://www.coinauthentication.co.uk/CCNindex.html", 
    "volume": null, 
    "year": null, 
    "zotero_id": null
}