{
    "description": "JERICHO MAFJAR PROJECT AND ISLAMIC ARCHAEOLOGY. Donald Whitcomb KERKENES DAG PROJECT. Scott Branting", 
    "domain": "oi.uchicago.edu", 
    "identifiers": {}, 
    "is_part_of": {
        "title": "Open Access Oriental Institute Annual Reports", 
        "url": "http://oi.uchicago.edu/research/pubs/ar/10-11/"
    }, 
    "keywords": [
        "project", 
        "religion", 
        "Islam"
    ], 
    "language": null, 
    "provenance": [], 
    "related_resources": [], 
    "subordinate_resources": [], 
    "title": "JERICHO MAFJAR PROJECT AND ISLAMIC ARCHAEOLOGY. Donald Whitcomb", 
    "url": "http://oi.uchicago.edu/pdf/10_11_Mafjar.pdf", 
    "volume": null, 
    "year": null, 
    "zotero_id": null
}