{
    "authors": [], 
    "contributors": [], 
    "description": "OIP 66. Post-Ramessid Remains. The Excavation of Medinet Habu, Volume 5. By Uvo H\u00f6lscher. Originally published in 1954.", 
    "domain": "oi.uchicago.edu", 
    "editors": [], 
    "end_date": null, 
    "extent": null, 
    "form": null, 
    "frequency": null, 
    "identifiers": {}, 
    "is_part_of": {
        "title_full": "OINE 2. Ausgrabungen von Khor-Dehmit bis Bet El-Wali. H. Ricke. Originally published in 1967", 
        "url": "http://oi.uchicago.edu/research/pubs/catalog/oine/oine2.html"
    }, 
    "issuance": null, 
    "issue": null, 
    "issued_dates": null, 
    "keywords": [
        "document", 
        "Egyptian", 
        "Oriental Institute", 
        "museums", 
        "book", 
        "Book of the Dead"
    ], 
    "languages": [
        "en"
    ], 
    "places": [], 
    "provenance": [
        {
            "fields": [
                "authors", 
                "contributors", 
                "description", 
                "domain", 
                "editors", 
                "end_date", 
                "extent", 
                "form", 
                "frequency", 
                "identifiers", 
                "is_part_of", 
                "issuance", 
                "issue", 
                "issued_dates", 
                "keywords", 
                "languages", 
                "places", 
                "provenance", 
                "publishers", 
                "related_resources", 
                "responsibility", 
                "start_date", 
                "subordinate_resources", 
                "title", 
                "title_alternates", 
                "title_extended", 
                "type", 
                "url", 
                "url_alternates", 
                "volume", 
                "year", 
                "zenon_id", 
                "zotero_id"
            ], 
            "resource": "tag:blogger.com,1999:blog-116259103207720939.post-673709284168022240", 
            "resource_date": "2009-06-26T13:21:14.172-04:00", 
            "term": "http://purl.org/spar/cito/citesAsDataSource", 
            "when": "2015-07-11T20:13:28.756477"
        }, 
        {
            "resource": "http://ancientworldonline.blogspot.com/2009/06/eleven-additional-books-from-oriental.html", 
            "resource_date": "2009-06-26T13:21:14.172-04:00", 
            "term": "http://purl.org/spar/cito/citesAsMetadataDocument", 
            "when": "2015-07-11T20:13:28.756495"
        }
    ], 
    "publishers": [], 
    "related_resources": [], 
    "resource_key": "research-pubs-catalog-oip-oip82-html", 
    "responsibility": [], 
    "start_date": null, 
    "subordinate_resources": [], 
    "title": "OIP 82. The Egyptian Book of the Dead: Documents in the Oriental Institute Museum at the University of Chicago. Edited by Thomas George Allen. Originally published in 1960", 
    "title_alternates": [], 
    "title_extended": null, 
    "type": null, 
    "url": "http://oi.uchicago.edu/research/pubs/catalog/oip/oip82.html", 
    "url_alternates": [], 
    "volume": null, 
    "year": null, 
    "zenon_id": null, 
    "zotero_id": null
}