{
    "description": "Journal of the County Louth Archaeological Society [1904-1969] (1393-2195) Release Content: Vol. 1, No. 1 (July, 1904) \u2013 Vol. 17, No. 1 (1969); Vol. 17, No. 2 (1970) \u2013 Vol. 26, No. 1 (2005) Moving Wall: 3 years Publisher: County Louth Archaeological and History Society ISSN: 0070-1327 Journal of the Royal Society of Antiquaries of Ireland", 
    "domain": "www.jstor.org", 
    "identifiers": {
        "issn": {
            "generic": [
                "0070-1327"
            ]
        }
    }, 
    "is_part_of": {
        "issn": "0790-892X", 
        "title": "New Ancient World Content in JSTOR", 
        "url": "http://www.jstor.org/page/info/about/archives/collections.jsp"
    }, 
    "keywords": [
        "journal", 
        "archaeology", 
        "Ireland", 
        "history"
    ], 
    "language": [
        "en", 
        1.0
    ], 
    "provenance": [], 
    "related_resources": [], 
    "subordinate_resources": [], 
    "title": "Journal of the County Louth Archaeological Society", 
    "url": "http://www.jstor.org/action/showPublication?journalCode=jcounloutarchsoc", 
    "volume": null, 
    "year": null, 
    "zotero_id": null
}