{
    "authors": [], 
    "contributors": [], 
    "description": "Republic of Cyprus: Department of Antiquities. On our website you can find information, both in Greek and English, concerning the history, the mission and the responsibilities of the Department of Antiquities. You can also be informed on the legislative framework that governs the antiquities of Cyprus, the publications of the Department, the educational and european programmes and the excavations that take place on the island as well as the looting of the island's cultural heritage in the occupied part of Cyprus. The site also includes downloadable applications on matters that concern the Department of Antiquities. The largest part of the website contains information concerning public museums and all visitable ancient monuments and archaeological sites. Apart from the historical and archaeological facts, practical information regarding the opening hours, public holidays and ticket prices are included. The Department of Antiquities' website will be constantly enriched with new information and will include announcements concerning the activities of the Department of Antiquities and other matters related to the archaeology of Cyprus.", 
    "domain": "www.mcw.gov.cy", 
    "editors": [], 
    "end_date": null, 
    "extent": null, 
    "form": null, 
    "frequency": null, 
    "identifiers": {}, 
    "is_part_of": {
        "title_full": "Republic of Cyprus: Department of Antiquities", 
        "url": "http://www.mcw.gov.cy/mcw/DA/DA.nsf/DMLindex_en/DMLindex_en?OpenDocument"
    }, 
    "issuance": null, 
    "issue": null, 
    "issued_dates": null, 
    "keywords": [], 
    "languages": [
        "en"
    ], 
    "places": [], 
    "provenance": [
        {
            "fields": [
                "authors", 
                "contributors", 
                "description", 
                "domain", 
                "editors", 
                "end_date", 
                "extent", 
                "form", 
                "frequency", 
                "identifiers", 
                "is_part_of", 
                "issuance", 
                "issue", 
                "issued_dates", 
                "keywords", 
                "languages", 
                "places", 
                "provenance", 
                "publishers", 
                "related_resources", 
                "responsibility", 
                "start_date", 
                "subordinate_resources", 
                "title", 
                "title_alternates", 
                "title_extended", 
                "type", 
                "url", 
                "url_alternates", 
                "volume", 
                "year", 
                "zenon_id", 
                "zotero_id"
            ], 
            "resource": "tag:blogger.com,1999:blog-116259103207720939.post-8404888829214801713", 
            "resource_date": "2015-03-30T11:36:44.332-04:00", 
            "term": "http://purl.org/spar/cito/citesAsDataSource", 
            "when": "2015-07-11T20:15:25.029931"
        }, 
        {
            "resource": "http://ancientworldonline.blogspot.com/2015/03/republic-of-cyprus-department-of.html", 
            "resource_date": "2015-03-30T11:36:44.332-04:00", 
            "term": "http://purl.org/spar/cito/citesAsMetadataDocument", 
            "when": "2015-07-11T20:15:25.029945"
        }
    ], 
    "publishers": [], 
    "related_resources": [], 
    "resource_key": "def3cfe414a1584bc95aebc331b1f70e5610e21f", 
    "responsibility": [], 
    "start_date": null, 
    "subordinate_resources": [], 
    "title": "News", 
    "title_alternates": [], 
    "title_extended": null, 
    "type": null, 
    "url": "http://www.mcw.gov.cy/mcw/DA/DA.nsf/DMLnews_en/DMLnews_en?OpenDocument", 
    "url_alternates": [], 
    "volume": null, 
    "year": null, 
    "zenon_id": null, 
    "zotero_id": null
}