{
    "description": "Archaeology 2.0: New Approaches to Communication and Collaboration, 2011 How is the Web transforming the professional practice of archaeology? And as archaeologists accustomed to dealing with \u201cdeep time,\u201d how can we best understand the possibilities and limitations of the Web in meeting the specialized... Wendrich, Willeke: The World According to Basketry, 1999 This book was originally published in 1999 by the Leiden University, Center of\u00a0Non-Western Studies. This is an unabridged re-publication of the 1999 edition,\u00a0and the one-hour movie that is an integral part of the book. You...", 
    "domain": "escholarship.org", 
    "identifiers": {}, 
    "is_part_of": {
        "title": "Cotsen Digital Archaeology", 
        "url": "http://escholarship.org/uc/search?entity=cioa_cda"
    }, 
    "keywords": [
        "website", 
        "collaboration", 
        "book", 
        "archaeology"
    ], 
    "language": [
        "en", 
        1.0
    ], 
    "provenance": [
        {
            "fields": [
                "description", 
                "domain", 
                "identifiers", 
                "is_part_of", 
                "keywords", 
                "language", 
                "provenance", 
                "related_resources", 
                "subordinate_resources", 
                "title", 
                "url", 
                "volume", 
                "year", 
                "zotero_id"
            ], 
            "resource": "tag:blogger.com,1999:blog-116259103207720939.post-3599524801723515230", 
            "resource_date": "2012-10-02T06:23:06.296-04:00", 
            "term": "http://purl.org/spar/cito/citesAsDataSource", 
            "when": "2015-06-11T20:12:40.101962"
        }, 
        {
            "resource": "http://ancientworldonline.blogspot.com/2012/10/open-access-book-series-cotsen-digital.html", 
            "resource_date": "2012-10-02T06:23:06.296-04:00", 
            "term": "http://purl.org/spar/cito/citesAsMetadataDocument", 
            "when": "2015-06-11T20:12:40.101976"
        }
    ], 
    "related_resources": [], 
    "subordinate_resources": [], 
    "title": "Archaeology 2.0: New Approaches to Communication and Collaboration", 
    "url": "http://escholarship.org/uc/item/1r6137tb", 
    "volume": null, 
    "year": null, 
    "zotero_id": null
}