{
    "description": "[First posted in AWOL 26 April 2011. Updated 17 October 2012] Institut National du Patrimoine Tunisie, Biblioth\u00e8que Num\u00e9rique: feuilles 1/50 000 1903-1904, 1905-1906, 1907-1908, 1925-1926, 1934: Bizerte, Cap-Bon, El Jem, Gab\u00e8s, Kairouan, La Goulette, Mahres, Maktar, Souk el Arba, Sousse, Tunis: 1951, 1953, 1955, 1956, 1957, 1958-1959, 1960-1961", 
    "domain": "www.inp.rnrt.tn", 
    "identifiers": {}, 
    "is_part_of": null, 
    "keywords": [
        "Tunisia", 
        "archaeology", 
        "digital library"
    ], 
    "language": [
        "fr", 
        1.0
    ], 
    "provenance": [
        {
            "fields": [
                "description", 
                "domain", 
                "identifiers", 
                "is_part_of", 
                "keywords", 
                "language", 
                "provenance", 
                "related_resources", 
                "subordinate_resources", 
                "title", 
                "url", 
                "volume", 
                "year", 
                "zotero_id"
            ], 
            "resource": "tag:blogger.com,1999:blog-116259103207720939.post-937761268721486799", 
            "resource_date": "2013-05-07T11:41:49.933-04:00", 
            "term": "http://purl.org/spar/cito/citesAsDataSource", 
            "when": "2015-06-11T20:14:44.784740"
        }, 
        {
            "resource": "http://ancientworldonline.blogspot.com/2011/04/digital-library-institut-national-du.html", 
            "resource_date": "2013-05-07T11:41:49.933-04:00", 
            "term": "http://purl.org/spar/cito/citesAsMetadataDocument", 
            "when": "2015-06-11T20:14:44.784757"
        }
    ], 
    "related_resources": [], 
    "subordinate_resources": [
        "http://www.inp.rnrt.tn/periodiques/bultin/b_arch_sousse_1903_1904.pdf", 
        "http://www.inp.rnrt.tn/periodiques/bultin/b_arch_sousse_1905_1906.pdf", 
        "http://www.inp.rnrt.tn/periodiques/bultin/b_arch_sousse_1907_1908.pdf", 
        "http://www.inp.rnrt.tn/periodiques/bultin/b_arch_sousse_1925_1926.pdf", 
        "http://www.inp.rnrt.tn/periodiques/bultin/b_arch_sousse_1934.pdf", 
        "http://www.inp.rnrt.tn/periodiques/atals/Bizerte.pdf", 
        "http://www.inp.rnrt.tn/periodiques/atals/Cap_Bon.pdf", 
        "http://www.inp.rnrt.tn/periodiques/atals/El_%20Djem.pdf", 
        "http://www.inp.rnrt.tn/periodiques/atals/Gabes.pdf", 
        "http://www.inp.rnrt.tn/periodiques/atals/Kairouan.pdf", 
        "http://www.inp.rnrt.tn/periodiques/atals/La_Goulette.pdf", 
        "http://www.inp.rnrt.tn/periodiques/atals/Mahres.pdf", 
        "http://www.inp.rnrt.tn/periodiques/atals/Maktar.pdf", 
        "http://www.inp.rnrt.tn/periodiques/atals/Souk_el_Arba.pdf", 
        "http://www.inp.rnrt.tn/periodiques/atals/Sousse.pdf", 
        "http://www.inp.rnrt.tn/periodiques/atals/Tunis.pdf", 
        "http://www.inp.rnrt.tn/periodiques/cahier/cahiers_byrsa_1951.pdf", 
        "http://www.inp.rnrt.tn/periodiques/cahier/cahiers_byrsa_1953.pdf", 
        "http://www.inp.rnrt.tn/periodiques/cahier/cahiers_byrsa_1955.pdf", 
        "http://www.inp.rnrt.tn/periodiques/cahier/cahiers_byrsa_1956.pdf", 
        "http://www.inp.rnrt.tn/periodiques/cahier/cahiers_byrsa_1957.pdf", 
        "http://www.inp.rnrt.tn/periodiques/cahier/cahiers_byrsa_1958-1959.pdf", 
        "http://www.inp.rnrt.tn/periodiques/cahier/cahiers_byrsa_1960-1961.pdf"
    ], 
    "title": "Institut National du Patrimoine, Tunis", 
    "url": "http://www.inp.rnrt.tn/", 
    "volume": null, 
    "year": null, 
    "zotero_id": null
}