{
    "description": "[ 14-1 ] [ 14-2 ]", 
    "domain": "www.persee.fr", 
    "identifiers": {}, 
    "is_part_of": {
        "issn": "1957-701X", 
        "title": "Pal\u00e9orient", 
        "url": "http://www.persee.fr/web/revues/home/prescript/revue/paleo"
    }, 
    "keywords": [], 
    "language": null, 
    "provenance": [], 
    "related_resources": [], 
    "subordinate_resources": [], 
    "title": "14-1", 
    "url": "http://www.persee.fr/web/revues/home/prescript/issue/paleo_0153-9345_1988_num_14_1", 
    "volume": "14-1", 
    "year": "1988", 
    "zotero_id": null
}