{
    "authors": [], 
    "contributors": [], 
    "description": "The Society also publishes a quarterly journal, the Proceedings. The first volume of the Proceedings published in 1838. Articles in the journal include papers read at the Society's biannual meetings, independent essays sent to the APS by outside scholars, and biographical memoirs of Society members. Recent issues are available online on the APS website. See the full.", 
    "domain": "www.amphilsoc.org", 
    "editors": [], 
    "end_date": null, 
    "extent": null, 
    "form": null, 
    "frequency": null, 
    "identifiers": {}, 
    "is_part_of": {
        "title_full": "Proceedings of the American Philosophical Society", 
        "url": "http://www.amphilsoc.org/publications/proceedings"
    }, 
    "issuance": null, 
    "issue": null, 
    "issued_dates": null, 
    "keywords": [
        "proceedings", 
        "journal", 
        "open access"
    ], 
    "languages": [
        "en"
    ], 
    "places": [], 
    "provenance": [
        {
            "fields": [
                "authors", 
                "contributors", 
                "description", 
                "domain", 
                "editors", 
                "end_date", 
                "extent", 
                "form", 
                "frequency", 
                "identifiers", 
                "is_part_of", 
                "issuance", 
                "issue", 
                "issued_dates", 
                "keywords", 
                "languages", 
                "places", 
                "provenance", 
                "publishers", 
                "related_resources", 
                "responsibility", 
                "start_date", 
                "subordinate_resources", 
                "title", 
                "title_alternates", 
                "title_extended", 
                "type", 
                "url", 
                "url_alternates", 
                "volume", 
                "year", 
                "zenon_id", 
                "zotero_id"
            ], 
            "resource": "tag:blogger.com,1999:blog-116259103207720939.post-6917475422564531069", 
            "resource_date": "2012-05-22T09:26:59.370-04:00", 
            "term": "http://purl.org/spar/cito/citesAsDataSource", 
            "when": "2015-07-11T20:13:37.504475"
        }, 
        {
            "resource": "http://ancientworldonline.blogspot.com/2012/05/open-access-journal-proceedings-of.html", 
            "resource_date": "2012-05-22T09:26:59.370-04:00", 
            "term": "http://purl.org/spar/cito/citesAsMetadataDocument", 
            "when": "2015-07-11T20:13:37.504494"
        }, 
        {
            "fields": [
                "authors", 
                "contributors", 
                "description", 
                "domain", 
                "editors", 
                "end_date", 
                "extent", 
                "form", 
                "frequency", 
                "identifiers", 
                "is_part_of", 
                "issuance", 
                "issue", 
                "issued_dates", 
                "keywords", 
                "languages", 
                "places", 
                "provenance", 
                "publishers", 
                "related_resources", 
                "responsibility", 
                "start_date", 
                "subordinate_resources", 
                "title", 
                "title_alternates", 
                "title_extended", 
                "type", 
                "url", 
                "url_alternates", 
                "volume", 
                "year", 
                "zenon_id", 
                "zotero_id"
            ], 
            "resource": "tag:blogger.com,1999:blog-116259103207720939.post-6917475422564531069", 
            "resource_date": "2012-05-22T09:26:59.370-04:00", 
            "term": "http://purl.org/spar/cito/citesAsDataSource", 
            "when": "2015-07-11T20:13:37.508257"
        }, 
        {
            "resource": "http://ancientworldonline.blogspot.com/2012/05/open-access-journal-proceedings-of.html", 
            "resource_date": "2012-05-22T09:26:59.370-04:00", 
            "term": "http://purl.org/spar/cito/citesAsMetadataDocument", 
            "when": "2015-07-11T20:13:37.508269"
        }, 
        {
            "fields": [
                "subordinate_resources", 
                "resource_key", 
                "keywords", 
                "languages", 
                "description", 
                "is_part_of", 
                "identifiers"
            ], 
            "resource": "http://purl.org/net/wf-motifs#Combine", 
            "term": "http://purl.org/net/wf-motifs#hasWorkflowMotif", 
            "when": "2015-07-11T20:13:37.509669"
        }
    ], 
    "publishers": [], 
    "related_resources": [], 
    "resource_key": "publications-proceedings", 
    "responsibility": [], 
    "start_date": null, 
    "subordinate_resources": [
        {
            "title_full": "Proceedings of the American Philosophical Society", 
            "url": "http://www.amphilsoc.org/publications/proceedings"
        }
    ], 
    "title": "Proceedings of the American Philosophical Society", 
    "title_alternates": [], 
    "title_extended": null, 
    "type": null, 
    "url": "http://www.amphilsoc.org/publications/proceedings", 
    "url_alternates": [], 
    "volume": null, 
    "year": null, 
    "zenon_id": null, 
    "zotero_id": null
}