{
    "authors": [], 
    "contributors": [], 
    "description": "BSAA Arqueolog\u00eda: Bolet\u00edn del Seminario de Estudios de Arqueolog\u00eda (continuing.", 
    "domain": "dialnet.unirioja.es", 
    "editors": [], 
    "end_date": null, 
    "extent": null, 
    "form": null, 
    "frequency": null, 
    "identifiers": {}, 
    "is_part_of": null, 
    "issuance": null, 
    "issue": null, 
    "issued_dates": null, 
    "keywords": [
        "journal", 
        "archaeology", 
        "Spain", 
        "open access"
    ], 
    "languages": [
        "es"
    ], 
    "places": [], 
    "provenance": [
        {
            "fields": [
                "authors", 
                "contributors", 
                "description", 
                "domain", 
                "editors", 
                "end_date", 
                "extent", 
                "form", 
                "frequency", 
                "identifiers", 
                "is_part_of", 
                "issuance", 
                "issue", 
                "issued_dates", 
                "keywords", 
                "languages", 
                "places", 
                "provenance", 
                "publishers", 
                "related_resources", 
                "responsibility", 
                "start_date", 
                "subordinate_resources", 
                "title", 
                "title_alternates", 
                "title_extended", 
                "type", 
                "url", 
                "url_alternates", 
                "volume", 
                "year", 
                "zenon_id", 
                "zotero_id"
            ], 
            "resource": "tag:blogger.com,1999:blog-116259103207720939.post-7680663990464356791", 
            "resource_date": "2014-06-01T07:56:15.005-04:00", 
            "term": "http://purl.org/spar/cito/citesAsDataSource", 
            "when": "2015-07-11T20:14:42.136058"
        }, 
        {
            "resource": "http://ancientworldonline.blogspot.com/2011/05/open-access-journal-bsaa-arqueologia.html", 
            "resource_date": "2014-06-01T07:56:15.005-04:00", 
            "term": "http://purl.org/spar/cito/citesAsMetadataDocument", 
            "when": "2015-07-11T20:14:42.136076"
        }
    ], 
    "publishers": [], 
    "related_resources": [], 
    "resource_key": "fd9f4ccfde1d2925145b6dc2a90cefa26d2f7980", 
    "responsibility": [], 
    "start_date": null, 
    "subordinate_resources": [
        {
            "title_full": "Bolet\u00edn del Seminario de Estudios de Arte y Arqueolog\u00eda", 
            "url": "http://dialnet.unirioja.es/servlet/revista?codigo=226"
        }, 
        {
            "title_full": "2011-2012", 
            "url": "http://dialnet.unirioja.es/servlet/listaarticulos?tipoDeBusqueda=ANUALIDAD&revistaDeBusqueda=15437&claveDeBusqueda=2011"
        }, 
        {
            "title_full": "77-78", 
            "url": "http://dialnet.unirioja.es/servlet/ejemplar?codigo=336602"
        }, 
        {
            "title_full": "2010", 
            "url": "http://dialnet.unirioja.es/servlet/listaarticulos?tipoDeBusqueda=ANUALIDAD&revistaDeBusqueda=15437&claveDeBusqueda=2010"
        }, 
        {
            "title_full": "76", 
            "url": "http://dialnet.unirioja.es/servlet/ejemplar?codigo=295289"
        }, 
        {
            "title_full": "2009", 
            "url": "http://dialnet.unirioja.es/servlet/listaarticulos?tipoDeBusqueda=ANUALIDAD&revistaDeBusqueda=15437&claveDeBusqueda=2009"
        }, 
        {
            "title_full": "75", 
            "url": "http://dialnet.unirioja.es/servlet/ejemplar?codigo=277712"
        }, 
        {
            "title_full": "2008", 
            "url": "http://dialnet.unirioja.es/servlet/listaarticulos?tipoDeBusqueda=ANUALIDAD&revistaDeBusqueda=15437&claveDeBusqueda=2008"
        }, 
        {
            "title_full": "74 (1)", 
            "url": "http://dialnet.unirioja.es/servlet/ejemplar?codigo=275970"
        }, 
        {
            "title_full": "2006-2007", 
            "url": "http://dialnet.unirioja.es/servlet/listaarticulos?tipoDeBusqueda=ANUALIDAD&revistaDeBusqueda=15437&claveDeBusqueda=2006"
        }, 
        {
            "title_full": "72-73 (1)", 
            "url": "http://dialnet.unirioja.es/servlet/ejemplar?codigo=275968"
        }, 
        {
            "title_full": "2005", 
            "url": "http://dialnet.unirioja.es/servlet/listaarticulos?tipoDeBusqueda=ANUALIDAD&revistaDeBusqueda=15437&claveDeBusqueda=2005"
        }, 
        {
            "title_full": "71 (1)", 
            "url": "http://dialnet.unirioja.es/servlet/ejemplar?codigo=275967"
        }
    ], 
    "title": "BSAA Arqueolog\u00eda: Bolet\u00edn del Seminario de Estudios de Arqueolog\u00eda", 
    "title_alternates": [], 
    "title_extended": null, 
    "type": null, 
    "url": "http://dialnet.unirioja.es/servlet/revista?codigo=15437", 
    "url_alternates": [], 
    "volume": null, 
    "year": null, 
    "zenon_id": null, 
    "zotero_id": null
}