{
    "description": "\u25aa Vladimir Sazonov, Ludlul B\u0113l Nem\u0113qi: The Standard Babylonian Poem of the Righteous Sufferer \u2013 Amar Anus and Alan Lenzi \u25aa Vladimir Sazonov, Ludlul B\u0113l Nem\u0113qi: The Standard Babylonian Poem of the Righteous Sufferer \u2013 Amar Anus and Alan Lenzi.", 
    "domain": "www.fcsh.unl.pt", 
    "identifiers": {}, 
    "is_part_of": {
        "issn": "1647-7642", 
        "title": "Kubaba", 
        "url": "http://www.fcsh.unl.pt/~kubaba/KUBABA/index.html"
    }, 
    "keywords": [
        "Babylon", 
        "Amar"
    ], 
    "language": [
        "en", 
        1.0
    ], 
    "provenance": [
        {
            "fields": [
                "description", 
                "domain", 
                "identifiers", 
                "is_part_of", 
                "keywords", 
                "language", 
                "provenance", 
                "related_resources", 
                "subordinate_resources", 
                "title", 
                "url", 
                "volume", 
                "year", 
                "zotero_id"
            ], 
            "resource": "tag:blogger.com,1999:blog-116259103207720939.post-1318044479732731848", 
            "resource_date": "2013-03-18T21:10:20.917-04:00", 
            "term": "http://purl.org/spar/cito/citesAsDataSource", 
            "when": "2015-06-13T16:11:34.328630"
        }, 
        {
            "resource": "http://ancientworldonline.blogspot.com/2010/07/new-open-access-journal-kubaba.html", 
            "resource_date": "2013-03-18T21:10:20.917-04:00", 
            "term": "http://purl.org/spar/cito/citesAsMetadataDocument", 
            "when": "2015-06-13T16:11:34.328646"
        }
    ], 
    "related_resources": [], 
    "subordinate_resources": [], 
    "title": "\u25aa Vladimir Sazonov, Ludlul B\u0113l Nem\u0113qi: The Standard Babylonian Poem of the Righteous Sufferer \u2013 Amar Anus and Alan Lenzi", 
    "url": "http://www.fcsh.unl.pt/%7Ekubaba/KUBABA/k_3_2012_texts/SAZONOV_2012.pdf", 
    "volume": null, 
    "year": null, 
    "zotero_id": null
}