{
    "description": "MORE Alexandria and Alexandrianism John Walsh, Thomas F. Reese, Peter Green, Henri Riad, Diana Delia, Gunter Grimm, Lilly Kahil, Heinrich von Staden, Judith McKenzie, John Onians, W. A. Daszewski, Klaus Parlasca, Michael Pfrommer, Robert Steven Bianchi, R. R. R. Smith, Bernard V. Bothmer, Andrew Stewart, Arielle P. Kozloff, G. W. Bowersock, Abraham L. Udovitch, Mohamed Ghoneim 1996 MORE", 
    "domain": "www.getty.edu", 
    "identifiers": {}, 
    "is_part_of": {
        "title": "Getty Publications Virtual Library", 
        "url": "http://www.getty.edu/publications/virtuallibrary/index.html"
    }, 
    "keywords": [], 
    "language": null, 
    "provenance": [
        {
            "fields": [
                "description", 
                "domain", 
                "identifiers", 
                "is_part_of", 
                "keywords", 
                "language", 
                "provenance", 
                "related_resources", 
                "subordinate_resources", 
                "title", 
                "url", 
                "volume", 
                "year", 
                "zotero_id"
            ], 
            "resource": "tag:blogger.com,1999:blog-116259103207720939.post-1697581904695761075", 
            "resource_date": "2014-01-21T14:33:21.633-05:00", 
            "term": "http://purl.org/spar/cito/citesAsDataSource", 
            "when": "2015-06-11T20:11:50.413431"
        }, 
        {
            "resource": "http://ancientworldonline.blogspot.com/2014/01/just-announced-getty-publications.html", 
            "resource_date": "2014-01-21T14:33:21.633-05:00", 
            "term": "http://purl.org/spar/cito/citesAsMetadataDocument", 
            "when": "2015-06-11T20:11:50.413445"
        }
    ], 
    "related_resources": [], 
    "subordinate_resources": [], 
    "title": "MORE", 
    "url": "http://www.getty.edu/publications/virtuallibrary/0892360178.html?subject=antq&pg=3&res=20", 
    "volume": null, 
    "year": null, 
    "zotero_id": null
}