{
    "description": "Video-Ta p ed Presentations Video-Ta p ed Presentations", 
    "domain": "www.genizah.org", 
    "identifiers": {}, 
    "is_part_of": {
        "title": "The Friedberg Genizah Project (FGP)", 
        "url": "http://www.genizah.org/"
    }, 
    "keywords": [
        "presentations"
    ], 
    "language": null, 
    "provenance": [], 
    "related_resources": [], 
    "subordinate_resources": [], 
    "title": "Video-Taped Presentations", 
    "url": "http://www.genizah.org/VideoTapedPresentations.aspx", 
    "volume": "-", 
    "year": null, 
    "zotero_id": null
}