{
    "description": "Can Poetry be Translated? Third part of the What is Translation podcast series. In this part, the question of whether poetry be translated. Is there something within the original that is lost in the translation? 0:16:09 Oliver Taplin,", 
    "domain": "www.podcasts.ox.ac.uk", 
    "identifiers": {}, 
    "is_part_of": {
        "title": "University of Oxford Podcasts: Faculty of Classics", 
        "url": "http://www.podcasts.ox.ac.uk/units/faculty-classics"
    }, 
    "keywords": [
        "poetry"
    ], 
    "language": [
        "en", 
        1.0
    ], 
    "provenance": [], 
    "related_resources": [], 
    "subordinate_resources": [], 
    "title": "Can Poetry be Translated?", 
    "url": "http://www.podcasts.ox.ac.uk/can-poetry-be-translated-audio", 
    "volume": null, 
    "year": null, 
    "zotero_id": null
}