{
    "description": "Koran Collection Collection of Qur'an and it\u2019s translations printed in various countries, which are available in the IRCICA Library Voyages in the Middle East Selected collection of media about Middle East and its history, culture & geography", 
    "domain": "e-library.ircica.org", 
    "identifiers": {}, 
    "is_part_of": {
        "title": "Ircica Farabi Digital Library", 
        "url": "http://e-library.ircica.org/"
    }, 
    "keywords": [
        "culture", 
        "Middle East", 
        "geography"
    ], 
    "language": [
        "en", 
        1.0
    ], 
    "provenance": [], 
    "related_resources": [], 
    "subordinate_resources": [], 
    "title": "Koran Collection", 
    "url": "http://e-library.ircica.org/search/?act=direct-search&collections=8", 
    "volume": null, 
    "year": null, 
    "zotero_id": null
}