{
    "description": "Symeonis Junioris. *121: *\u0393\u03b5\u03c9\u03c1\u03b3\u03af\u03bf\u03c5 \u03c4\u03bf\u03c5 \u039a\u03b5\u03b4\u03c1\u03b7\u03bd\u03bf\u03cd \u03a3\u03cd\u03bd\u03bf\u03c8\u03b9\u03c2 \u03b9\u03c3\u03c4\u03bf\u03c1\u03b9\u03ce\u03bd. \u03a4\u03bf\u03bc. \u0391\u0384. Georgiou tou Kedrenou Synopsis historion: cui subjiciuntur excerpta ex breviario Joannis Scylitzae Curopalatae. Tomus prior. 1894. Georgii Cedreni 1. (\u039a\u03b5\u03b4\u03c1\u03b5\u03bd\u03cc\u03c2 \u0393\u03b5\u03ce\u03c1\u03b3\u03b9\u03bf\u03c2, \u03a3\u03cd\u03bd\u03bf\u03c8\u03b9\u03c2 \u0399\u03c3\u03c4\u03bf\u03c1\u03b9\u03ce\u03bd.", 
    "domain": "khazarzar.skeptik.net", 
    "identifiers": {}, 
    "is_part_of": {
        "title": "Migne online", 
        "url": "http://khazarzar.skeptik.net/pgm/index.htm"
    }, 
    "keywords": [], 
    "language": [
        "el", 
        1.0
    ], 
    "provenance": [], 
    "related_resources": [], 
    "subordinate_resources": [], 
    "title": "Symeonis Junioris", 
    "url": "http://khazarzar.skeptik.net/pgm/PG_Migne/Symeonis%20Junioris_PG%20120", 
    "volume": null, 
    "year": null, 
    "zotero_id": null
}